Edit_History_Api/__init__.py
Edit_History_Api/edit_history_api.py
Edit_History_API_JMills-0.1.dist-info/METADATA
Edit_History_API_JMills-0.1.dist-info/WHEEL
Edit_History_API_JMills-0.1.dist-info/top_level.txt
Edit_History_API_JMills-0.1.dist-info/RECORD
