Metadata-Version: 2.1
Name: Edit-History-API-JMills
Version: 0.1
Summary: A simple module with classes for managing edits in a Wiki system.
Home-page: UNKNOWN
Author: Jeff Mills
Author-email: millsj12@nku.edu
License: UNKNOWN
Platform: UNKNOWN
